fidelity/__init__.py
fidelity/__main__.py
fidelity/cli.py
fidelity/fidelity.py
rlane_fidelity-1.0.3.dist-info/METADATA
rlane_fidelity-1.0.3.dist-info/WHEEL
rlane_fidelity-1.0.3.dist-info/entry_points.txt
rlane_fidelity-1.0.3.dist-info/licenses/LICENSE
rlane_fidelity-1.0.3.dist-info/RECORD
