Metadata-Version: 2.1
Name: rlane-fidelity
Version: 1.0.3
Summary: Process Fidelity transaction files
Keywords: fidelity,python,trading,stocks,reports
Author-Email: Russel Lane <russel@rlane.com>
License: MIT
Classifier: Development Status :: 4 - Beta
Classifier: Intended Audience :: End Users/Desktop
Classifier: License :: OSI Approved :: MIT License
Classifier: Programming Language :: Python :: 3
Classifier: Topic :: Office/Business :: Financial
Project-URL: Homepage, https://github.com/russellane/fidelity
Requires-Python: >=3.10
Requires-Dist: rich>=13.9.4
Requires-Dist: rlane-libcli>=1.0.8
